streamlit_jet/__init__.py
streamlit_jet/Button/__init__.py
streamlit_jet/Button/frontend/build/asset-manifest.json
streamlit_jet/Button/frontend/build/bootstrap.min.css
streamlit_jet/Button/frontend/build/index.html
streamlit_jet/Button/frontend/build/precache-manifest.483a98280e4e85e77d602aa7120b91f0.js
streamlit_jet/Button/frontend/build/precache-manifest.9d9ef00e6838a62b5cb0fb11bcbae659.js
streamlit_jet/Button/frontend/build/service-worker.js
streamlit_jet/Button/frontend/build/static/css/2.4d2f809d.chunk.css
streamlit_jet/Button/frontend/build/static/css/2.4d2f809d.chunk.css.map
streamlit_jet/Button/frontend/build/static/css/main.10a697f7.chunk.css
streamlit_jet/Button/frontend/build/static/css/main.10a697f7.chunk.css.map
streamlit_jet/Button/frontend/build/static/css/main.63a875e8.chunk.css
streamlit_jet/Button/frontend/build/static/css/main.63a875e8.chunk.css.map
streamlit_jet/Button/frontend/build/static/js/2.7dd2628c.chunk.js
streamlit_jet/Button/frontend/build/static/js/2.7dd2628c.chunk.js.LICENSE.txt
streamlit_jet/Button/frontend/build/static/js/2.7dd2628c.chunk.js.map
streamlit_jet/Button/frontend/build/static/js/2.b35a80ad.chunk.js
streamlit_jet/Button/frontend/build/static/js/2.b35a80ad.chunk.js.LICENSE.txt
streamlit_jet/Button/frontend/build/static/js/2.b35a80ad.chunk.js.map
streamlit_jet/Button/frontend/build/static/js/main.35a6668f.chunk.js
streamlit_jet/Button/frontend/build/static/js/main.35a6668f.chunk.js.map
streamlit_jet/Button/frontend/build/static/js/main.795b6e4f.chunk.js
streamlit_jet/Button/frontend/build/static/js/main.795b6e4f.chunk.js.map
streamlit_jet/Button/frontend/build/static/js/runtime-main.96bfec46.js
streamlit_jet/Button/frontend/build/static/js/runtime-main.96bfec46.js.map
streamlit_jet/Button/frontend/build/static/media/bootstrap-icons.1ed478a6.woff2
streamlit_jet/Button/frontend/build/static/media/bootstrap-icons.e4cc83dd.woff
streamlit_jet/ButtonBar/__init__.py
streamlit_jet/ButtonBar/frontend/build/asset-manifest.json
streamlit_jet-0.1.6.dist-info/METADATA
streamlit_jet-0.1.6.dist-info/WHEEL
streamlit_jet-0.1.6.dist-info/top_level.txt
streamlit_jet-0.1.6.dist-info/RECORD
