Metadata-Version: 2.1
Name: streamlit-jet
Version: 0.1.6
Summary: streamlit components
Author: jet
License: UNKNOWN
Platform: UNKNOWN
Requires-Python: >=3.9
Requires-Dist: streamlit (>=0.86)
